{ "_version":"1.0", "metadata":{ "FORMAT":{ "value":"1A" } }, "name":"", "description":"", "resourceGroups":[ { "name":"All Methods", "description":"", "resources":[ { "name":"", "description":"", "uriTemplate":"/v2/{tenant_id}/consistency-groups", "parameters":{ "tenant_id":{ "description":"\n The tenant ID in a multi-tenancy cloud.\n", "type":"csapi:UUID", "required":"", "default":"", "example":"", "values":[  ] } }, "headers":{ "X-Openstack-Manila-Api-Version":{ "description":"\n A valid Shared File Systems API micro-version.\n For example,\n \"X-Openstack-Manila-Api-Version: 2.6\".\n If you omit this header, the default micro-version is 2.0.\n \n", "type":"xsd:string", "required":"", "default":"", "example":"", "values":[  ] }, "X-OpenStack-Manila-API-Experimental":{ "description":"\n \n Indicates that this is an experimental Shared File\n Systems API request. Set to true.\n For example,\n \"X-OpenStack-Manila-API-Experimental: true\".\n \n", "type":"xsd:bool", "required":"true", "default":"", "example":"", "values":[  ] } }, "actions":[ { "method":"POST", "name":"Create consistency group", "description":"\n Creates a consistency group.\n", "parameters":{  }, "headers":{  }, "examples":[ { "name":"", "description":"", "requests":[ { "name":"", "description":"", "headers":{ "Content-Type":{ "value":"application/json" } }, "body":"{\n \"consistency_group\": {\n \"share_types\": [\n \"d2ad4f9d-cae3-4660-b0b6-58c06b385203\"\n ],\n \"name\": \"my-cg1\",\n \"share_network_id\": \"d8ae6799-2567-4a89-aafb-fa4424350d2b\",\n \"description\": \"my first consistency group\"\n }\n}\n", "schema":"" } ], "responses":[ { "name":"200", "description":"", "headers":{ "Content-Type":{ "value":"application/json" } }, "body":"{\n \"consistency_group\": {\n \"status\": \"creating\",\n \"description\": \"my first consistency group\",\n \"links\": [\n {\n \"href\": \"http:\/\/172.18.198.54:8786\/v2\/16e1ab15c35a457e9c2b2aa189f544e1\/consistency_groups\/6f519a48-3183-46cf-a32f-41815f813986\",\n \"rel\": \"self\"\n },\n {\n \"href\": \"http:\/\/172.18.198.54:8786\/16e1ab15c35a457e9c2b2aa189f544e1\/consistency_groups\/6f519a48-3183-46cf-a32f-41815f813986\",\n \"rel\": \"bookmark\"\n }\n ],\n \"source_cgsnapshot_id\": null,\n \"created_at\": \"2015-09-16T09:28:52.880949\",\n \"share_network_id\": \"d8ae6799-2567-4a89-aafb-fa4424350d2b\",\n \"host\": null,\n \"project_id\": \"16e1ab15c35a457e9c2b2aa189f544e1\",\n \"share_types\": [\n \"d2ad4f9d-cae3-4660-b0b6-58c06b385203\"\n ],\n \"id\": \"6f519a48-3183-46cf-a32f-41815f813986\",\n \"name\": \"my-cg1\"\n }\n}\n", "schema":"" } ] } ] }, { "method":"GET", "name":"List consistency groups", "description":"\n Lists all consistency groups.\n", "parameters":{  }, "headers":{  }, "examples":[ { "name":"", "description":"", "requests":[  ], "responses":[ { "name":"200", "description":"", "headers":{ "Content-Type":{ "value":"application/json" } }, "body":"{\n \"consistency_groups\": [\n {\n \"id\": \"6f519a48-3183-46cf-a32f-41815f813986\",\n \"links\": [\n {\n \"href\": \"http:\/\/172.18.198.54:8786\/v2\/16e1ab15c35a457e9c2b2aa189f544e1\/consistency_groups\/6f519a48-3183-46cf-a32f-41815f813986\",\n \"rel\": \"self\"\n },\n {\n \"href\": \"http:\/\/172.18.198.54:8786\/16e1ab15c35a457e9c2b2aa189f544e1\/consistency_groups\/6f519a48-3183-46cf-a32f-41815f813986\",\n \"rel\": \"bookmark\"\n }\n ],\n \"name\": \"my-cg1\"\n },\n {\n \"id\": \"aed36625-a6d7-4681-ba59-c7ba3d18c148\",\n \"links\": [\n {\n \"href\": \"http:\/\/172.18.198.54:8786\/v2\/16e1ab15c35a457e9c2b2aa189f544e1\/consistency_groups\/aed36625-a6d7-4681-ba59-c7ba3d18c148\",\n \"rel\": \"self\"\n },\n {\n \"href\": \"http:\/\/172.18.198.54:8786\/16e1ab15c35a457e9c2b2aa189f544e1\/consistency_groups\/aed36625-a6d7-4681-ba59-c7ba3d18c148\",\n \"rel\": \"bookmark\"\n }\n ],\n \"name\": \"my-cg2\"\n }\n ]\n}\n", "schema":"" } ] } ] } ] }, { "name":"", "description":"", "uriTemplate":"/v2/{tenant_id}/consistency-groups/detail", "parameters":{ "tenant_id":{ "description":"\n The tenant ID in a multi-tenancy cloud.\n", "type":"csapi:UUID", "required":"", "default":"", "example":"", "values":[  ] } }, "headers":{ "X-Openstack-Manila-Api-Version":{ "description":"\n A valid Shared File Systems API micro-version.\n For example,\n \"X-Openstack-Manila-Api-Version: 2.6\".\n If you omit this header, the default micro-version is 2.0.\n \n", "type":"xsd:string", "required":"", "default":"", "example":"", "values":[  ] }, "X-OpenStack-Manila-API-Experimental":{ "description":"\n \n Indicates that this is an experimental Shared File\n Systems API request. Set to true.\n For example,\n \"X-OpenStack-Manila-API-Experimental: true\".\n \n", "type":"xsd:bool", "required":"true", "default":"", "example":"", "values":[  ] } }, "actions":[ { "method":"GET", "name":"List consistency groups with details", "description":"\n Lists all consistency groups with details.\n", "parameters":{  }, "headers":{  }, "examples":[ { "name":"", "description":"", "requests":[  ], "responses":[ { "name":"200", "description":"", "headers":{ "Content-Type":{ "value":"application/json" } }, "body":"{\n \"consistency_groups\": [\n {\n \"status\": \"available\",\n \"description\": \"my first consistency group\",\n \"links\": [\n {\n \"href\": \"http:\/\/172.18.198.54:8786\/v2\/16e1ab15c35a457e9c2b2aa189f544e1\/consistency_groups\/6f519a48-3183-46cf-a32f-41815f813986\",\n \"rel\": \"self\"\n },\n {\n \"href\": \"http:\/\/172.18.198.54:8786\/16e1ab15c35a457e9c2b2aa189f544e1\/consistency_groups\/6f519a48-3183-46cf-a32f-41815f813986\",\n \"rel\": \"bookmark\"\n }\n ],\n \"source_cgsnapshot_id\": null,\n \"created_at\": \"2015-09-16T09:28:52.000000\",\n \"share_network_id\": \"d8ae6799-2567-4a89-aafb-fa4424350d2b\",\n \"host\": null,\n \"project_id\": \"16e1ab15c35a457e9c2b2aa189f544e1\",\n \"share_types\": [\n \"d2ad4f9d-cae3-4660-b0b6-58c06b385203\"\n ],\n \"id\": \"6f519a48-3183-46cf-a32f-41815f813986\",\n \"name\": \"my-cg1\"\n },\n {\n \"status\": \"error\",\n \"description\": \"Edited description\",\n \"links\": [\n {\n \"href\": \"http:\/\/172.18.198.54:8786\/v2\/16e1ab15c35a457e9c2b2aa189f544e1\/consistency_groups\/aed36625-a6d7-4681-ba59-c7ba3d18c148\",\n \"rel\": \"self\"\n },\n {\n \"href\": \"http:\/\/172.18.198.54:8786\/16e1ab15c35a457e9c2b2aa189f544e1\/consistency_groups\/aed36625-a6d7-4681-ba59-c7ba3d18c148\",\n \"rel\": \"bookmark\"\n }\n ],\n \"source_cgsnapshot_id\": null,\n \"created_at\": \"2015-09-16T09:31:15.000000\",\n \"share_network_id\": \"713df749-aac0-4a54-af52-10f6c991e80c\",\n \"host\": null,\n \"project_id\": \"16e1ab15c35a457e9c2b2aa189f544e1\",\n \"share_types\": [\n \"be27425c-f807-4500-a056-d00721db45cf\"\n ],\n \"id\": \"aed36625-a6d7-4681-ba59-c7ba3d18c148\",\n \"name\": \"my-cg2\"\n }\n ]\n}\n", "schema":"" } ] } ] } ] }, { "name":"", "description":"", "uriTemplate":"/v2/{tenant_id}/consistency-groups/{consistency_group_id}", "parameters":{ "tenant_id":{ "description":"\n The tenant ID in a multi-tenancy cloud.\n", "type":"csapi:UUID", "required":"", "default":"", "example":"", "values":[  ] }, "consistency_group_id":{ "description":"\n The unique identifier of the consistency group.\n", "type":"csapi:UUID", "required":"", "default":"", "example":"", "values":[  ] } }, "headers":{ "X-Openstack-Manila-Api-Version":{ "description":"\n A valid Shared File Systems API micro-version.\n For example,\n \"X-Openstack-Manila-Api-Version: 2.6\".\n If you omit this header, the default micro-version is 2.0.\n \n", "type":"xsd:string", "required":"", "default":"", "example":"", "values":[  ] }, "X-OpenStack-Manila-API-Experimental":{ "description":"\n \n Indicates that this is an experimental Shared File\n Systems API request. Set to true.\n For example,\n \"X-OpenStack-Manila-API-Experimental: true\".\n \n", "type":"xsd:bool", "required":"true", "default":"", "example":"", "values":[  ] } }, "actions":[ { "method":"GET", "name":"Show consistency group", "description":"\n Shows information about a specified consistency group.\n", "parameters":{  }, "headers":{  }, "examples":[ { "name":"", "description":"", "requests":[  ], "responses":[ { "name":"200", "description":"", "headers":{ "Content-Type":{ "value":"application/json" } }, "body":"{\n \"consistency_group\": {\n \"status\": \"available\",\n \"description\": \"My first CG.\",\n \"links\": [\n {\n \"href\": \"http:\/\/172.18.198.54:8786\/v2\/16e1ab15c35a457e9c2b2aa189f544e1\/consistency_groups\/9397c191-8427-4661-a2e8-b23820dc01d4\",\n \"rel\": \"self\"\n },\n {\n \"href\": \"http:\/\/172.18.198.54:8786\/16e1ab15c35a457e9c2b2aa189f544e1\/consistency_groups\/9397c191-8427-4661-a2e8-b23820dc01d4\",\n \"rel\": \"bookmark\"\n }\n ],\n \"source_cgsnapshot_id\": null,\n \"created_at\": \"2015-09-16T16:50:31.000000\",\n \"share_network_id\": \"f9b2e754-ac01-4466-86e1-5c569424754e\",\n \"share_server_id\": null,\n \"host\": \"manila2@generic1#GENERIC1\",\n \"project_id\": \"16e1ab15c35a457e9c2b2aa189f544e1\",\n \"share_types\": [\n \"be27425c-f807-4500-a056-d00721db45cf\"\n ],\n \"id\": \"9397c191-8427-4661-a2e8-b23820dc01d4\",\n \"name\": \"cg1\"\n }\n}\n", "schema":"" } ] } ] }, { "method":"PUT", "name":"Update consistency group", "description":"\n Updates a specified consistency group.\n You can update only these attributes:\n \n \n \n name, which changes the consistency group name.\n \n \n \n \n description, which changes the consistency group description.\n \n \n \n", "parameters":{  }, "headers":{  }, "examples":[ { "name":"", "description":"", "requests":[ { "name":"", "description":"", "headers":{ "Content-Type":{ "value":"application/json" } }, "body":"{\n \"consistency_group\": {\n \"description\": \"Edited description\"\n }\n}\n", "schema":"" } ], "responses":[ { "name":"200", "description":"", "headers":{ "Content-Type":{ "value":"application/json" } }, "body":"{\n \"consistency_group\": {\n \"status\": \"error\",\n \"description\": \"Edited description\",\n \"links\": [\n {\n \"href\": \"http:\/\/172.18.198.54:8786\/v2\/16e1ab15c35a457e9c2b2aa189f544e1\/consistency_groups\/aed36625-a6d7-4681-ba59-c7ba3d18c148\",\n \"rel\": \"self\"\n },\n {\n \"href\": \"http:\/\/172.18.198.54:8786\/16e1ab15c35a457e9c2b2aa189f544e1\/consistency_groups\/aed36625-a6d7-4681-ba59-c7ba3d18c148\",\n \"rel\": \"bookmark\"\n }\n ],\n \"source_cgsnapshot_id\": null,\n \"created_at\": \"2015-09-16T09:31:15.000000\",\n \"share_network_id\": \"713df749-aac0-4a54-af52-10f6c991e80c\",\n \"host\": null,\n \"project_id\": \"16e1ab15c35a457e9c2b2aa189f544e1\",\n \"share_types\": [\n \"be27425c-f807-4500-a056-d00721db45cf\"\n ],\n \"id\": \"aed36625-a6d7-4681-ba59-c7ba3d18c148\",\n \"name\": \"my-cg2\"\n }\n}\n", "schema":"" } ] } ] }, { "method":"DELETE", "name":"Delete consistency group", "description":"\n Deletes a specified consistency group.\n", "parameters":{  }, "headers":{  }, "examples":[ { "name":"", "description":"", "requests":[  ], "responses":[  ] } ] } ] }, { "name":"", "description":"", "uriTemplate":"/v2/{tenant_id}/consistency-groups/{consistency_group_id}/action", "parameters":{ "tenant_id":{ "description":"\n The tenant ID in a multi-tenancy cloud.\n", "type":"csapi:UUID", "required":"", "default":"", "example":"", "values":[  ] }, "consistency_group_id":{ "description":"\n The unique identifier of the consistency group.\n", "type":"csapi:UUID", "required":"", "default":"", "example":"", "values":[  ] } }, "headers":{ "X-Openstack-Manila-Api-Version":{ "description":"\n A valid Shared File Systems API micro-version.\n For example,\n \"X-Openstack-Manila-Api-Version: 2.6\".\n If you omit this header, the default micro-version is 2.0.\n \n", "type":"xsd:string", "required":"", "default":"", "example":"", "values":[  ] }, "X-OpenStack-Manila-API-Experimental":{ "description":"\n \n Indicates that this is an experimental Shared File\n Systems API request. Set to true.\n For example,\n \"X-OpenStack-Manila-API-Experimental: true\".\n \n", "type":"xsd:bool", "required":"true", "default":"", "example":"", "values":[  ] } }, "actions":[ { "method":"POST", "name":"Reset consistency group state", "description":"\n Administrator only. Explicitly updates the state of a specified consistency group.\n Use the policy.json file to grant permissions for this action to other roles.\n", "parameters":{  }, "headers":{  }, "examples":[ { "name":"", "description":"", "requests":[ { "name":"", "description":"", "headers":{ "Content-Type":{ "value":"application/json" } }, "body":"{\n \"os-reset_status\": {\n \"status\": \"available\"\n }\n}\n", "schema":"" } ], "responses":[  ] } ] }, { "method":"POST", "name":"Force-delete consistency group", "description":"\n Administrator only. Force-deletes a specified consistency group.\n Use the policy.json file to grant permissions for this action to other roles.\n", "parameters":{  }, "headers":{  }, "examples":[ { "name":"", "description":"", "requests":[ { "name":"", "description":"", "headers":{ "Content-Type":{ "value":"application/json" } }, "body":"{\n \"os-force_delete\": null\n}\n", "schema":"" } ], "responses":[  ] } ] } ] }, { "name":"", "description":"", "uriTemplate":"/v2/{tenant_id}/cgsnapshots", "parameters":{ "tenant_id":{ "description":"\n The tenant ID in a multi-tenancy cloud.\n", "type":"csapi:UUID", "required":"", "default":"", "example":"", "values":[  ] } }, "headers":{ "X-Openstack-Manila-Api-Version":{ "description":"\n A valid Shared File Systems API micro-version.\n For example,\n \"X-Openstack-Manila-Api-Version: 2.6\".\n If you omit this header, the default micro-version is 2.0.\n \n", "type":"xsd:string", "required":"", "default":"", "example":"", "values":[  ] }, "X-OpenStack-Manila-API-Experimental":{ "description":"\n \n Indicates that this is an experimental Shared File\n Systems API request. Set to true.\n For example,\n \"X-OpenStack-Manila-API-Experimental: true\".\n \n", "type":"xsd:bool", "required":"true", "default":"", "example":"", "values":[  ] } }, "actions":[ { "method":"POST", "name":"Create consistency group snapshot", "description":"\n Creates a consistency group snapshot.\n \n You can create a consistency group snapshot for a consistency group\n in available state only.\n \n", "parameters":{  }, "headers":{  }, "examples":[ { "name":"", "description":"", "requests":[ { "name":"", "description":"", "headers":{ "Content-Type":{ "value":"application/json" } }, "body":"{\n \"cgsnapshot\": {\n \"consistency_group_id\": \"9397c191-8427-4661-a2e8-b23820dc01d4\",\n \"name\": \"snapshot_cg1\",\n \"description\": \"Snapshot of cg1\"\n }\n}\n", "schema":"" } ], "responses":[ { "name":"200", "description":"", "headers":{ "Content-Type":{ "value":"application/json" } }, "body":"{\n \"cgsnapshot\": {\n \"status\": \"creating\",\n \"name\": \"snapshot_cg1\",\n \"links\": [\n {\n \"href\": \"http:\/\/172.18.198.54:8786\/v2\/16e1ab15c35a457e9c2b2aa189f544e1\/cgsnapshot\/b44c894d-4bec-47aa-b389-cc8c6f0044a5\",\n \"rel\": \"self\"\n },\n {\n \"href\": \"http:\/\/172.18.198.54:8786\/16e1ab15c35a457e9c2b2aa189f544e1\/cgsnapshot\/b44c894d-4bec-47aa-b389-cc8c6f0044a5\",\n \"rel\": \"bookmark\"\n }\n ],\n \"created_at\": \"2015-09-16T17:34:06.031997\",\n \"consistency_group_id\": \"9397c191-8427-4661-a2e8-b23820dc01d4\",\n \"project_id\": \"16e1ab15c35a457e9c2b2aa189f544e1\",\n \"id\": \"b44c894d-4bec-47aa-b389-cc8c6f0044a5\",\n \"description\": \"Snapshot of cg1\"\n }\n}\n", "schema":"" } ] } ] }, { "method":"GET", "name":"List consistency group snapshots", "description":"\n Lists all consistency group snapshots.\n", "parameters":{  }, "headers":{  }, "examples":[ { "name":"", "description":"", "requests":[  ], "responses":[ { "name":"200", "description":"", "headers":{ "Content-Type":{ "value":"application/json" } }, "body":"{\n \"cgsnapshots\": [\n {\n \"id\": \"7e5c3ca7-d54b-438d-9a9c-c65ece6bc6c6\",\n \"links\": [\n {\n \"href\": \"http:\/\/172.18.198.54:8786\/v2\/16e1ab15c35a457e9c2b2aa189f544e1\/cgsnapshot\/7e5c3ca7-d54b-438d-9a9c-c65ece6bc6c6\",\n \"rel\": \"self\"\n },\n {\n \"href\": \"http:\/\/172.18.198.54:8786\/16e1ab15c35a457e9c2b2aa189f544e1\/cgsnapshot\/7e5c3ca7-d54b-438d-9a9c-c65ece6bc6c6\",\n \"rel\": \"bookmark\"\n }\n ],\n \"name\": \"snapshot_CG2\"\n },\n {\n \"id\": \"b44c894d-4bec-47aa-b389-cc8c6f0044a5\",\n \"links\": [\n {\n \"href\": \"http:\/\/172.18.198.54:8786\/v2\/16e1ab15c35a457e9c2b2aa189f544e1\/cgsnapshot\/b44c894d-4bec-47aa-b389-cc8c6f0044a5\",\n \"rel\": \"self\"\n },\n {\n \"href\": \"http:\/\/172.18.198.54:8786\/16e1ab15c35a457e9c2b2aa189f544e1\/cgsnapshot\/b44c894d-4bec-47aa-b389-cc8c6f0044a5\",\n \"rel\": \"bookmark\"\n }\n ],\n \"name\": \"snapshot_cg1\"\n }\n ]\n}\n", "schema":"" } ] } ] } ] }, { "name":"", "description":"", "uriTemplate":"/v2/{tenant_id}/cgsnapshots/detail", "parameters":{ "tenant_id":{ "description":"\n The tenant ID in a multi-tenancy cloud.\n", "type":"csapi:UUID", "required":"", "default":"", "example":"", "values":[  ] } }, "headers":{ "X-Openstack-Manila-Api-Version":{ "description":"\n A valid Shared File Systems API micro-version.\n For example,\n \"X-Openstack-Manila-Api-Version: 2.6\".\n If you omit this header, the default micro-version is 2.0.\n \n", "type":"xsd:string", "required":"", "default":"", "example":"", "values":[  ] }, "X-OpenStack-Manila-API-Experimental":{ "description":"\n \n Indicates that this is an experimental Shared File\n Systems API request. Set to true.\n For example,\n \"X-OpenStack-Manila-API-Experimental: true\".\n \n", "type":"xsd:bool", "required":"true", "default":"", "example":"", "values":[  ] } }, "actions":[ { "method":"GET", "name":"List consistency group snapshots with details", "description":"\n Lists all consistency group snapshots with details.\n", "parameters":{  }, "headers":{  }, "examples":[ { "name":"", "description":"", "requests":[  ], "responses":[ { "name":"200", "description":"", "headers":{ "Content-Type":{ "value":"application/json" } }, "body":"{\n \"cgsnapshots\": [\n {\n \"status\": \"available\",\n \"name\": \"snapshot_CG2\",\n \"links\": [\n {\n \"href\": \"http:\/\/172.18.198.54:8786\/v2\/16e1ab15c35a457e9c2b2aa189f544e1\/cgsnapshot\/7e5c3ca7-d54b-438d-9a9c-c65ece6bc6c6\",\n \"rel\": \"self\"\n },\n {\n \"href\": \"http:\/\/172.18.198.54:8786\/16e1ab15c35a457e9c2b2aa189f544e1\/cgsnapshot\/7e5c3ca7-d54b-438d-9a9c-c65ece6bc6c6\",\n \"rel\": \"bookmark\"\n }\n ],\n \"created_at\": \"2015-09-16T17:37:40.000000\",\n \"consistency_group_id\": \"2d5c2600-ae67-4dff-b13c-a1c20b335e8e\",\n \"project_id\": \"16e1ab15c35a457e9c2b2aa189f544e1\",\n \"id\": \"7e5c3ca7-d54b-438d-9a9c-c65ece6bc6c6\",\n \"description\": \"Snapshot of CG2\"\n },\n {\n \"status\": \"available\",\n \"name\": \"snapshot_cg1\",\n \"links\": [\n {\n \"href\": \"http:\/\/172.18.198.54:8786\/v2\/16e1ab15c35a457e9c2b2aa189f544e1\/cgsnapshot\/b44c894d-4bec-47aa-b389-cc8c6f0044a5\",\n \"rel\": \"self\"\n },\n {\n \"href\": \"http:\/\/172.18.198.54:8786\/16e1ab15c35a457e9c2b2aa189f544e1\/cgsnapshot\/b44c894d-4bec-47aa-b389-cc8c6f0044a5\",\n \"rel\": \"bookmark\"\n }\n ],\n \"created_at\": \"2015-09-16T17:34:15.000000\",\n \"consistency_group_id\": \"9397c191-8427-4661-a2e8-b23820dc01d4\",\n \"project_id\": \"16e1ab15c35a457e9c2b2aa189f544e1\",\n \"id\": \"b44c894d-4bec-47aa-b389-cc8c6f0044a5\",\n \"description\": \"Snapshot of cg1\"\n }\n ]\n}\n", "schema":"" } ] } ] } ] }, { "name":"", "description":"", "uriTemplate":"/v2/{tenant_id}/cgsnapshots/{cgsnapshot_id}", "parameters":{ "tenant_id":{ "description":"\n The tenant ID in a multi-tenancy cloud.\n", "type":"csapi:UUID", "required":"", "default":"", "example":"", "values":[  ] }, "cgsnapshot_id":{ "description":"\n The unique identifier of the consistency group snapshot.\n", "type":"csapi:UUID", "required":"", "default":"", "example":"", "values":[  ] } }, "headers":{ "X-Openstack-Manila-Api-Version":{ "description":"\n A valid Shared File Systems API micro-version.\n For example,\n \"X-Openstack-Manila-Api-Version: 2.6\".\n If you omit this header, the default micro-version is 2.0.\n \n", "type":"xsd:string", "required":"", "default":"", "example":"", "values":[  ] }, "X-OpenStack-Manila-API-Experimental":{ "description":"\n \n Indicates that this is an experimental Shared File\n Systems API request. Set to true.\n For example,\n \"X-OpenStack-Manila-API-Experimental: true\".\n \n", "type":"xsd:bool", "required":"true", "default":"", "example":"", "values":[  ] } }, "actions":[ { "method":"GET", "name":"Show consistency group snapshot", "description":"\n Shows information about a specified consistency group snapshot.\n", "parameters":{  }, "headers":{  }, "examples":[ { "name":"", "description":"", "requests":[  ], "responses":[ { "name":"200", "description":"", "headers":{ "Content-Type":{ "value":"application/json" } }, "body":"{\n \"cgsnapshot\": {\n \"status\": \"available\",\n \"name\": \"snapshot_cg1\",\n \"links\": [\n {\n \"href\": \"http:\/\/172.18.198.54:8786\/v2\/16e1ab15c35a457e9c2b2aa189f544e1\/cgsnapshot\/b44c894d-4bec-47aa-b389-cc8c6f0044a5\",\n \"rel\": \"self\"\n },\n {\n \"href\": \"http:\/\/172.18.198.54:8786\/16e1ab15c35a457e9c2b2aa189f544e1\/cgsnapshot\/b44c894d-4bec-47aa-b389-cc8c6f0044a5\",\n \"rel\": \"bookmark\"\n }\n ],\n \"created_at\": \"2015-09-16T17:34:15.000000\",\n \"consistency_group_id\": \"9397c191-8427-4661-a2e8-b23820dc01d4\",\n \"project_id\": \"16e1ab15c35a457e9c2b2aa189f544e1\",\n \"id\": \"b44c894d-4bec-47aa-b389-cc8c6f0044a5\",\n \"description\": \"Snapshot of cg1\"\n }\n}\n", "schema":"" } ] } ] }, { "method":"PUT", "name":"Update consistency group snapshot", "description":"\n Updates a specified consistency group snapshot.\n You can update only these attributes:\n \n \n \n name, which changes the consistency group snapshot name.\n \n \n \n \n description, which changes the consistency group snapshot description.\n \n \n \n", "parameters":{  }, "headers":{  }, "examples":[ { "name":"", "description":"", "requests":[ { "name":"", "description":"", "headers":{ "Content-Type":{ "value":"application/json" } }, "body":"{\n \"cgsnapshot\": {\n \"description\": \"Changed description: there is a snapshot of CG2\"\n }\n}\n", "schema":"" } ], "responses":[ { "name":"200", "description":"", "headers":{ "Content-Type":{ "value":"application/json" } }, "body":"{\n \"cgsnapshot\": {\n \"status\": \"available\",\n \"name\": \"snapshot_CG2\",\n \"links\": [\n {\n \"href\": \"http:\/\/172.18.198.54:8786\/v2\/16e1ab15c35a457e9c2b2aa189f544e1\/cgsnapshot\/7e5c3ca7-d54b-438d-9a9c-c65ece6bc6c6\",\n \"rel\": \"self\"\n },\n {\n \"href\": \"http:\/\/172.18.198.54:8786\/16e1ab15c35a457e9c2b2aa189f544e1\/cgsnapshot\/7e5c3ca7-d54b-438d-9a9c-c65ece6bc6c6\",\n \"rel\": \"bookmark\"\n }\n ],\n \"created_at\": \"2015-09-16T17:37:40.000000\",\n \"consistency_group_id\": \"2d5c2600-ae67-4dff-b13c-a1c20b335e8e\",\n \"project_id\": \"16e1ab15c35a457e9c2b2aa189f544e1\",\n \"id\": \"7e5c3ca7-d54b-438d-9a9c-c65ece6bc6c6\",\n \"description\": \"Changed description: there is a snapshot of CG2\"\n }\n}\n", "schema":"" } ] } ] }, { "method":"DELETE", "name":"Delete consistency group snapshot", "description":"\n Deletes a specified consistency group snapshot.\n", "parameters":{  }, "headers":{  }, "examples":[ { "name":"", "description":"", "requests":[  ], "responses":[  ] } ] } ] }, { "name":"", "description":"", "uriTemplate":"/v2/{tenant_id}/cgsnapshots/{cgsnapshot_id}/members", "parameters":{ "tenant_id":{ "description":"\n The tenant ID in a multi-tenancy cloud.\n", "type":"csapi:UUID", "required":"", "default":"", "example":"", "values":[  ] }, "cgsnapshot_id":{ "description":"\n The unique identifier of the consistency group snapshot.\n", "type":"csapi:UUID", "required":"", "default":"", "example":"", "values":[  ] } }, "headers":{ "X-Openstack-Manila-Api-Version":{ "description":"\n A valid Shared File Systems API micro-version.\n For example,\n \"X-Openstack-Manila-Api-Version: 2.6\".\n If you omit this header, the default micro-version is 2.0.\n \n", "type":"xsd:string", "required":"", "default":"", "example":"", "values":[  ] }, "X-OpenStack-Manila-API-Experimental":{ "description":"\n \n Indicates that this is an experimental Shared File\n Systems API request. Set to true.\n For example,\n \"X-OpenStack-Manila-API-Experimental: true\".\n \n", "type":"xsd:bool", "required":"true", "default":"", "example":"", "values":[  ] } }, "actions":[ { "method":"GET", "name":"Show consistency group snapshot member", "description":"\n Shows information about a specified consistency group snapshot member.\n", "parameters":{  }, "headers":{  }, "examples":[ { "name":"", "description":"", "requests":[  ], "responses":[ { "name":"200", "description":"", "headers":{ "Content-Type":{ "value":"application/json" } }, "body":"{\n \"cgsnapshot_members\": [\n {\n \"share_type_id\": \"be27425c-f807-4500-a056-d00721db45cf\",\n \"share_id\": \"609e4924-f062-45e0-928d-7b739348c4d6\",\n \"created_at\": \"2015-09-16T17:34:15.000000\",\n \"cgsnapshot_id\": \"b44c894d-4bec-47aa-b389-cc8c6f0044a5\",\n \"share_protocol\": \"NFS\",\n \"project_id\": \"16e1ab15c35a457e9c2b2aa189f544e1\",\n \"id\": \"84098fde-40ec-4c96-a908-bc532c52b3af\",\n \"size\": 1\n },\n {\n \"share_type_id\": \"be27425c-f807-4500-a056-d00721db45cf\",\n \"share_id\": \"c4a2ced4-2c9f-4ae1-adaa-6171833e64df\",\n \"created_at\": \"2015-09-16T17:34:15.000000\",\n \"cgsnapshot_id\": \"b44c894d-4bec-47aa-b389-cc8c6f0044a5\",\n \"share_protocol\": \"NFS\",\n \"project_id\": \"16e1ab15c35a457e9c2b2aa189f544e1\",\n \"id\": \"db492d38-dd3a-4d6b-a3b6-e65377990892\",\n \"size\": 1\n }\n ]\n}\n", "schema":"" } ] } ] } ] }, { "name":"", "description":"", "uriTemplate":"/v2/{tenant_id}/cgsnapshots/{cgsnapshot_id}/action", "parameters":{ "tenant_id":{ "description":"\n The tenant ID in a multi-tenancy cloud.\n", "type":"csapi:UUID", "required":"", "default":"", "example":"", "values":[  ] }, "cgsnapshot_id":{ "description":"\n The unique identifier of the consistency group snapshot.\n", "type":"csapi:UUID", "required":"", "default":"", "example":"", "values":[  ] } }, "headers":{ "X-Openstack-Manila-Api-Version":{ "description":"\n A valid Shared File Systems API micro-version.\n For example,\n \"X-Openstack-Manila-Api-Version: 2.6\".\n If you omit this header, the default micro-version is 2.0.\n \n", "type":"xsd:string", "required":"", "default":"", "example":"", "values":[  ] }, "X-OpenStack-Manila-API-Experimental":{ "description":"\n \n Indicates that this is an experimental Shared File\n Systems API request. Set to true.\n For example,\n \"X-OpenStack-Manila-API-Experimental: true\".\n \n", "type":"xsd:bool", "required":"true", "default":"", "example":"", "values":[  ] } }, "actions":[ { "method":"POST", "name":"Reset consistency group snapshot state", "description":"\n Administrator only. Explicitly updates the state of a specified consistency group snapshot.\n Administrators can use the policy.json file to permit other roles to complete this action.\n", "parameters":{  }, "headers":{  }, "examples":[ { "name":"", "description":"", "requests":[ { "name":"", "description":"", "headers":{ "Content-Type":{ "value":"application/json" } }, "body":"{\n \"os-reset_status\": {\n \"status\": \"error\"\n }\n}\n", "schema":"" } ], "responses":[  ] } ] }, { "method":"POST", "name":"Force-delete consistency group snapshot", "description":"\n Administrator only. Force-deletes a specified consistency group snapshot.\n Use the policy.json file to grant permissions for this action to other roles.\n", "parameters":{  }, "headers":{  }, "examples":[ { "name":"", "description":"", "requests":[ { "name":"", "description":"", "headers":{ "Content-Type":{ "value":"application/json" } }, "body":"{\n \"os-force_delete\": null\n}\n", "schema":"" } ], "responses":[  ] } ] } ] } ] } ] }